{
    "response": {
        "header": {
            "resultCode": "00",
            "resultMsg": "NORMAL SERVICE."
        },
        "body": {
            "numOfRows": 10,
            "pageNo": 1,
            "totalCount": 3956845,
            "items": {
                "item": [
                    {
                        "basDt": "20251230",
                        "srtnCd": "900110",
                        "isinCd": "HK0000057197",
                        "itmsNm": "이스트아시아홀딩스",
                        "mrktCtg": "KOSDAQ",
                        "clpr": "1112",
                        "vs": "11",
                        "fltRt": "1",
                        "mkp": "1101",
                        "hipr": "1139",
                        "lopr": "1088",
                        "trqu": "62225",
                        "trPrc": "69130433",
                        "lstgStCnt": "26286743",
                        "mrktTotAmt": "29230858216"
                    },
                    {
                        "basDt": "20251230",
                        "srtnCd": "900270",
                        "isinCd": "HK0000214814",
                        "itmsNm": "헝셩그룹",
                        "mrktCtg": "KOSDAQ",
                        "clpr": "198",
                        "vs": "-1",
                        "fltRt": "-.5",
                        "mkp": "199",
                        "hipr": "199",
                        "lopr": "196",
                        "trqu": "1303422",
                        "trPrc": "260319720",
                        "lstgStCnt": "188047040",
                        "mrktTotAmt": "37233313920"
                    },
                    {
                        "basDt": "20251230",
                        "srtnCd": "900260",
                        "isinCd": "HK0000295359",
                        "itmsNm": "로스웰",
                        "mrktCtg": "KOSDAQ",
                        "clpr": "1572",
                        "vs": "-2",
                        "fltRt": "-.13",
                        "mkp": "1572",
                        "hipr": "1574",
                        "lopr": "1572",
                        "trqu": "296292",
                        "trPrc": "465798887",
                        "lstgStCnt": "46029706",
                        "mrktTotAmt": "72358697832"
                    },
                    {
                        "basDt": "20251230",
                        "srtnCd": "900290",
                        "isinCd": "HK0000307485",
                        "itmsNm": "GRT",
                        "mrktCtg": "KOSDAQ",
                        "clpr": "3110",
                        "vs": "-90",
                        "fltRt": "-2.81",
                        "mkp": "3220",
                        "hipr": "3220",
                        "lopr": "3110",
                        "trqu": "186352",
                        "trPrc": "587909170",
                        "lstgStCnt": "80850000",
                        "mrktTotAmt": "251443500000"
                    },
                    {
                        "basDt": "20251230",
                        "srtnCd": "900300",
                        "isinCd": "HK0000312568",
                        "itmsNm": "오가닉티코스메틱",
                        "mrktCtg": "KOSDAQ",
                        "clpr": "237",
                        "vs": "-6",
                        "fltRt": "-2.47",
                        "mkp": "245",
                        "hipr": "262",
                        "lopr": "233",
                        "trqu": "3502075",
                        "trPrc": "858776273",
                        "lstgStCnt": "251004876",
                        "mrktTotAmt": "59488155612"
                    },
                    {
                        "basDt": "20251230",
                        "srtnCd": "900310",
                        "isinCd": "HK0000341732",
                        "itmsNm": "컬러레이",
                        "mrktCtg": "KOSDAQ",
                        "clpr": "572",
                        "vs": "4",
                        "fltRt": ".7",
                        "mkp": "570",
                        "hipr": "578",
                        "lopr": "561",
                        "trqu": "123051",
                        "trPrc": "71147378",
                        "lstgStCnt": "64041675",
                        "mrktTotAmt": "36631838100"
                    },
                    {
                        "basDt": "20251230",
                        "srtnCd": "900340",
                        "isinCd": "HK0000449303",
                        "itmsNm": "윙입푸드",
                        "mrktCtg": "KOSDAQ",
                        "clpr": "800",
                        "vs": "11",
                        "fltRt": "1.39",
                        "mkp": "795",
                        "hipr": "801",
                        "lopr": "781",
                        "trqu": "61739",
                        "trPrc": "49107958",
                        "lstgStCnt": "50330928",
                        "mrktTotAmt": "40264742400"
                    },
                    {
                        "basDt": "20251230",
                        "srtnCd": "000020",
                        "isinCd": "KR7000020008",
                        "itmsNm": "동화약품",
                        "mrktCtg": "KOSPI",
                        "clpr": "6250",
                        "vs": "-40",
                        "fltRt": "-.64",
                        "mkp": "6270",
                        "hipr": "6290",
                        "lopr": "6220",
                        "trqu": "38814",
                        "trPrc": "242633955",
                        "lstgStCnt": "27931470",
                        "mrktTotAmt": "174571687500"
                    },
                    {
                        "basDt": "20251230",
                        "srtnCd": "000040",
                        "isinCd": "KR7000040006",
                        "itmsNm": "KR모터스",
                        "mrktCtg": "KOSPI",
                        "clpr": "451",
                        "vs": "-19",
                        "fltRt": "-4.04",
                        "mkp": "471",
                        "hipr": "475",
                        "lopr": "446",
                        "trqu": "614325",
                        "trPrc": "278459434",
                        "lstgStCnt": "86375184",
                        "mrktTotAmt": "38955207984"
                    },
                    {
                        "basDt": "20251230",
                        "srtnCd": "000050",
                        "isinCd": "KR7000050005",
                        "itmsNm": "경방",
                        "mrktCtg": "KOSPI",
                        "clpr": "9360",
                        "vs": "140",
                        "fltRt": "1.52",
                        "mkp": "9420",
                        "hipr": "9510",
                        "lopr": "9180",
                        "trqu": "302590",
                        "trPrc": "2833154290",
                        "lstgStCnt": "27415270",
                        "mrktTotAmt": "256606927200"
                    }
                ]
            }
        }
    }
}